snapatac2_scooby-1.0.3.dist-info/RECORD
snapatac2_scooby-1.0.3.dist-info/WHEEL
snapatac2_scooby-1.0.3.dist-info/METADATA
snapatac2_scooby-1.0.3.dist-info/licenses/LICENSE
snapatac2_scooby/_snapatac2.cpython-312-darwin.so
snapatac2_scooby/_io.py
snapatac2_scooby/datasets.py
snapatac2_scooby/__init__.py
snapatac2_scooby/genome.py
snapatac2_scooby/_utils.py
snapatac2_scooby/metrics/__init__.py
snapatac2_scooby/tools/_clustering.py
snapatac2_scooby/tools/_smooth.py
snapatac2_scooby/tools/_diff.py
snapatac2_scooby/tools/__init__.py
snapatac2_scooby/tools/_embedding.py
snapatac2_scooby/tools/_integration.py
snapatac2_scooby/tools/_network.py
snapatac2_scooby/tools/_call_peaks.py
snapatac2_scooby/tools/_motif.py
snapatac2_scooby/tools/_misc.py
snapatac2_scooby/plotting/_base.py
snapatac2_scooby/plotting/__init__.py
snapatac2_scooby/plotting/_network.py
snapatac2_scooby/preprocessing/_knn.py
snapatac2_scooby/preprocessing/_recipe.py
snapatac2_scooby/preprocessing/__init__.py
snapatac2_scooby/preprocessing/_scanorama.py
snapatac2_scooby/preprocessing/_scrublet.py
snapatac2_scooby/preprocessing/_cell_calling.py
snapatac2_scooby/preprocessing/_harmony.py
snapatac2_scooby/preprocessing/_mnn_correct.py
snapatac2_scooby/preprocessing/_basic.py
snapatac2_scooby/export/__init__.py
