Metadata-Version: 2.4
Name: snapatac2_scooby
Version: 1.0.3
Classifier: Programming Language :: Rust
Classifier: Programming Language :: Python :: Implementation :: CPython
Classifier: Programming Language :: Python :: Implementation :: PyPy
Classifier: License :: OSI Approved :: MIT License
Requires-Dist: anndata>=0.8.0,<0.11.0
Requires-Dist: kaleido
Requires-Dist: multiprocess
Requires-Dist: macs3>=3.0.3,<3.1
Requires-Dist: natsort
Requires-Dist: numpy>=1.16.0,<3.0.0
Requires-Dist: pandas>=1.0,<3.0.0
Requires-Dist: plotly>=5.19.0,<6.0.0
Requires-Dist: polars>=1.0,<2.0
Requires-Dist: pooch>=1.6.0,<2.0.0
Requires-Dist: igraph>=0.10.3
Requires-Dist: pyarrow<21.0.0
Requires-Dist: pyfaidx>=0.7.0,<0.8.0
Requires-Dist: rustworkx
Requires-Dist: scipy>=1.4,<2.0.0
Requires-Dist: scikit-learn>=1.0,<2.0.0
Requires-Dist: tqdm>=4.62
Requires-Dist: typeguard>=4.0
Requires-Dist: scanorama>=1.7.3 ; extra == 'recommend'
Requires-Dist: harmonypy>=0.0.9 ; extra == 'recommend'
Requires-Dist: xgboost>=1.4 ; extra == 'recommend'
Requires-Dist: umap-learn>=0.5.0 ; extra == 'recommend'
Requires-Dist: scanpy>=1.9 ; extra == 'recommend'
Requires-Dist: scvi-tools>=1.0 ; extra == 'recommend'
Requires-Dist: scikit-misc>=0.1.3 ; extra == 'recommend'
Requires-Dist: magic-impute>=2.0 ; extra == 'recommend'
Requires-Dist: pytest ; extra == 'test'
Requires-Dist: hypothesis==6.72.4 ; extra == 'test'
Provides-Extra: recommend
Provides-Extra: test
License-File: LICENSE
Summary: SnapATAC2-scooby: Single-cell epigenomics analysis pipeline with functionality for RNA-seq processing
Home-Page: https://github.com/
Author-email: Kai Zhang <zhangkai33@westlake.edu.cn>, Laura Martens <laura.d.martens@icloud.com>, Trevor Manz <trevor.j.manz@gmail.com>
Maintainer-email: Laura Martens <laura.d.martens@icloud.com>
Requires-Python: >=3.9, <3.14
Project-URL: Homepage, https://scooby.readthedocs.io/en/latest/
Project-URL: Documentation, https://scooby.readthedocs.io/en/latest/
Project-URL: Repository, https://scooby.readthedocs.io/en/latest/
Project-URL: Issues, https://github.com/lauradmartens/SnapATAC2/issues
